README
erst.py
setup.py
Erst.egg-info/PKG-INFO
Erst.egg-info/SOURCES.txt
Erst.egg-info/dependency_links.txt
Erst.egg-info/requires.txt
Erst.egg-info/top_level.txt