Metadata-Version: 1.0
Name: Erst
Version: 0.6
Summary: An automatic versioning fuse filesystem
Home-page: UNKNOWN
Author: Eric Estabrooks
Author-email: estabroo@gmail.com
License: Apache License 2.0 - http://www.apache.org/licenses/LICENSE-2.0.html
Keywords: erst mercurial revision versioning automatic
Platform: UNKNOWN
